{"config": {"view": {"continuousWidth": 300, "continuousHeight": 300, "strokeWidth": 0}, "locale": {"number": {"decimal": ",", "thousands": ".", "grouping": [3], "currency": ["", "\u00a0\u20ac"]}}, "title": {"dx": 60, "dy": -15, "fontSize": 15}}, "data": {"name": "data-6606d1e571586aaae30205f60fef8949"}, "mark": {"type": "bar"}, "encoding": {"color": {"field": "cat", "legend": {"labelFontSize": 12, "labelLimit": 0, "symbolSize": 400}, "scale": {"domain": ["S\u00ed", "No"], "reverse": true, "scheme": "spectral"}, "title": null, "type": "nominal"}, "column": {"field": "seg2", "header": {"labelFontSize": 15}, "sort": {"field": "order"}, "title": null, "type": "nominal"}, "order": {"field": "order", "sort": "descending", "type": "quantitative"}, "row": {"field": "seg1", "header": {"labelFontSize": 15}, "sort": {"field": "order"}, "title": null, "type": "nominal"}, "tooltip": [{"field": "cat", "title": "Valor", "type": "nominal"}, {"field": "prop", "format": ".2%", "title": "Estimaci\u00f3n", "type": "quantitative"}, {"field": "lower", "format": ".2%", "title": "L\u00edmite inferior", "type": "quantitative"}, {"field": "upper", "format": ".2%", "title": "L\u00edmite superior", "type": "quantitative"}], "x": {"axis": {"labelAngle": 0, "labelFontSize": 11}, "field": "M", "sort": {"field": "order"}, "title": null, "type": "nominal"}, "y": {"axis": {"format": "%", "labelFontSize": 11}, "field": "prop", "scale": {"nice": false}, "title": null, "type": "quantitative"}}, "height": 175, "params": [{"name": "param_3805", "select": {"type": "point", "fields": ["cat"], "on": "click", "toggle": "true"}, "bind": "legend"}, {"name": "param_3806", "select": {"type": "interval", "encodings": ["x", "y"]}, "bind": "scales"}], "resolve": {"axis": {"x": "independent", "y": "independent"}}, "title": {"text": ["Menores seg\u00fan si ha consumido antibi\u00f3ticos por edici\u00f3n, sexo y clase social del adulto (porcentajes e intervalos de confianza al 95%)"], "subtitle": "Fuente: Encuesta Andaluza de Salud (menores). C\u00f3digo de variable: IP16A05"}, "transform": [{"filter": {"param": "param_3805"}}, {"filter": "indexof(datum.M, '2') != -1"}], "width": {"step": 45, "for": "position"}, "$schema": "https://vega.github.io/schema/vega-lite/v5.17.0.json", "datasets": {"data-6606d1e571586aaae30205f60fef8949": [{"M": "2007", "seg1": "Ni\u00f1a", "seg2": "Grupo I y II", "cat": "S\u00ed", "prop": 0.04130726175899236, "lower": 0.0, "upper": 0.20636461232281691, "order": 0}, {"M": "2007", "seg1": "Ni\u00f1a", "seg2": "Grupo I y II", "cat": "No", "prop": 0.9586927382410076, "lower": 0.7936353876771856, "upper": 1.0, "order": 1}, {"M": "2007", "seg1": "Ni\u00f1a", "seg2": "Grupo III", "cat": "S\u00ed", "prop": 0.1006524270388314, "lower": 0.03163594409648298, "upper": 0.27320255438909385, "order": 2}, {"M": "2007", "seg1": "Ni\u00f1a", "seg2": "Grupo III", "cat": "No", "prop": 0.8993475729611686, "lower": 0.7267974456109063, "upper": 0.968364055903517, "order": 3}, {"M": "2007", "seg1": "Ni\u00f1a", "seg2": "Grupo IV y V", "cat": "S\u00ed", "prop": 0.0, "lower": 0.0, "upper": 0.10534757730523049, "order": 4}, {"M": "2007", "seg1": "Ni\u00f1a", "seg2": "Grupo IV y V", "cat": "No", "prop": 1.0, "lower": 0.8946524226947695, "upper": 1.0, "order": 5}, {"M": "2007", "seg1": "Ni\u00f1a", "seg2": "Grupo VI", "cat": "S\u00ed", "prop": 0.14342737973158434, "lower": 0.06934899927502867, "upper": 0.2514881862304736, "order": 6}, {"M": "2007", "seg1": "Ni\u00f1a", "seg2": "Grupo VI", "cat": "No", "prop": 0.8565726202684156, "lower": 0.7485118137695264, "upper": 0.9306510007249713, "order": 7}, {"M": "2007", "seg1": "Ni\u00f1a", "seg2": "Grupo VII", "cat": "S\u00ed", "prop": 0.09579554490531811, "lower": 0.027351819101230166, "upper": 0.24036345319041752, "order": 8}, {"M": "2007", "seg1": "Ni\u00f1a", "seg2": "Grupo VII", "cat": "No", "prop": 0.9042044550946818, "lower": 0.7596365468095827, "upper": 0.9726481808987698, "order": 9}, {"M": "2007", "seg1": "Ni\u00f1a", "seg2": "No ha trabajado", "cat": "S\u00ed", "prop": 0.0, "lower": 0.0, "upper": 0.1568712305049839, "order": 10}, {"M": "2007", "seg1": "Ni\u00f1a", "seg2": "No ha trabajado", "cat": "No", "prop": 1.0, "lower": 0.8431287694950161, "upper": 1.0, "order": 11}, {"M": "2007", "seg1": "Ni\u00f1a", "seg2": "Total", "cat": "S\u00ed", "prop": 0.08924831432567858, "lower": 0.054779615963801966, "upper": 0.14141598182566598, "order": 12}, {"M": "2007", "seg1": "Ni\u00f1a", "seg2": "Total", "cat": "No", "prop": 0.9107516856743214, "lower": 0.858584018174334, "upper": 0.9452203840361983, "order": 13}, {"M": "2007", "seg1": "Ni\u00f1o", "seg2": "Grupo I y II", "cat": "S\u00ed", "prop": 0.09135729576589875, "lower": 0.02798412136867938, "upper": 0.2437435296318436, "order": 14}, {"M": "2007", "seg1": "Ni\u00f1o", "seg2": "Grupo I y II", "cat": "No", "prop": 0.9086427042341012, "lower": 0.7562564703681564, "upper": 0.9720158786313206, "order": 15}, {"M": "2007", "seg1": "Ni\u00f1o", "seg2": "Grupo III", "cat": "S\u00ed", "prop": 0.21775320589339273, "lower": 0.0819060642412422, "upper": 0.40080592814700877, "order": 16}, {"M": "2007", "seg1": "Ni\u00f1o", "seg2": "Grupo III", "cat": "No", "prop": 0.7822467941066072, "lower": 0.5991940718529912, "upper": 0.9180939357587579, "order": 17}, {"M": "2007", "seg1": "Ni\u00f1o", "seg2": "Grupo IV y V", "cat": "S\u00ed", "prop": 0.12309373305305027, "lower": 0.03151575718598293, "upper": 0.27712735227078644, "order": 18}, {"M": "2007", "seg1": "Ni\u00f1o", "seg2": "Grupo IV y V", "cat": "No", "prop": 0.8769062669469497, "lower": 0.7228726477292128, "upper": 0.968484242814017, "order": 19}, {"M": "2007", "seg1": "Ni\u00f1o", "seg2": "Grupo VI", "cat": "S\u00ed", "prop": 0.14252715400004606, "lower": 0.0686108556944746, "upper": 0.2514263308492316, "order": 20}, {"M": "2007", "seg1": "Ni\u00f1o", "seg2": "Grupo VI", "cat": "No", "prop": 0.857472845999954, "lower": 0.7485736691507684, "upper": 0.9313891443055252, "order": 21}, {"M": "2007", "seg1": "Ni\u00f1o", "seg2": "Grupo VII", "cat": "S\u00ed", "prop": 0.025201370014046126, "lower": 0.0, "upper": 0.10647322094548103, "order": 22}, {"M": "2007", "seg1": "Ni\u00f1o", "seg2": "Grupo VII", "cat": "No", "prop": 0.9747986299859539, "lower": 0.8935267790545172, "upper": 1.0, "order": 23}, {"M": "2007", "seg1": "Ni\u00f1o", "seg2": "No ha trabajado", "cat": "S\u00ed", "prop": 0.0, "lower": 0.0, "upper": 0.10534757730523049, "order": 24}, {"M": "2007", "seg1": "Ni\u00f1o", "seg2": "No ha trabajado", "cat": "No", "prop": 1.0, "lower": 0.8946524226947695, "upper": 1.0, "order": 25}, {"M": "2007", "seg1": "Ni\u00f1o", "seg2": "Total", "cat": "S\u00ed", "prop": 0.10851856419581159, "lower": 0.07081849913036045, "upper": 0.16248375043981234, "order": 26}, {"M": "2007", "seg1": "Ni\u00f1o", "seg2": "Total", "cat": "No", "prop": 0.8914814358041884, "lower": 0.8375162495601877, "upper": 0.9291815008696395, "order": 27}, {"M": "2007", "seg1": "Total", "seg2": "Grupo I y II", "cat": "S\u00ed", "prop": 0.07062968141706226, "lower": 0.01784614458995512, "upper": 0.16388011991812218, "order": 28}, {"M": "2007", "seg1": "Total", "seg2": "Grupo I y II", "cat": "No", "prop": 0.9293703185829377, "lower": 0.8361198800818771, "upper": 0.9821538554100449, "order": 29}, {"M": "2007", "seg1": "Total", "seg2": "Grupo III", "cat": "S\u00ed", "prop": 0.15673361905812633, "lower": 0.07342119579558433, "upper": 0.26519136385965586, "order": 30}, {"M": "2007", "seg1": "Total", "seg2": "Grupo III", "cat": "No", "prop": 0.8432663809418737, "lower": 0.7348086361403441, "upper": 0.9265788042044157, "order": 31}, {"M": "2007", "seg1": "Total", "seg2": "Grupo IV y V", "cat": "S\u00ed", "prop": 0.08173045310955133, "lower": 0.020610985967803017, "upper": 0.18970085502020848, "order": 32}, {"M": "2007", "seg1": "Total", "seg2": "Grupo IV y V", "cat": "No", "prop": 0.9182695468904487, "lower": 0.8102991449797916, "upper": 0.9793890140321969, "order": 33}, {"M": "2007", "seg1": "Total", "seg2": "Grupo VI", "cat": "S\u00ed", "prop": 0.1429707698885285, "lower": 0.08745704401556428, "upper": 0.2185909367728827, "order": 34}, {"M": "2007", "seg1": "Total", "seg2": "Grupo VI", "cat": "No", "prop": 0.8570292301114715, "lower": 0.7814090632271176, "upper": 0.9125429559844357, "order": 35}, {"M": "2007", "seg1": "Total", "seg2": "Grupo VII", "cat": "S\u00ed", "prop": 0.05633279857471508, "lower": 0.013841584259127852, "upper": 0.13346010352959137, "order": 36}, {"M": "2007", "seg1": "Total", "seg2": "Grupo VII", "cat": "No", "prop": 0.9436672014252849, "lower": 0.8665398964704086, "upper": 0.9861584157408723, "order": 37}, {"M": "2007", "seg1": "Total", "seg2": "No ha trabajado", "cat": "S\u00ed", "prop": 0.0, "lower": 0.0, "upper": 0.06572490734117319, "order": 38}, {"M": "2007", "seg1": "Total", "seg2": "No ha trabajado", "cat": "No", "prop": 1.0, "lower": 0.9342750926588268, "upper": 1.0, "order": 39}, {"M": "2007", "seg1": "Total", "seg2": "Total", "cat": "S\u00ed", "prop": 0.0998886292995253, "lower": 0.07263535908646482, "upper": 0.13572409143062494, "order": 40}, {"M": "2007", "seg1": "Total", "seg2": "Total", "cat": "No", "prop": 0.9001113707004748, "lower": 0.8642759085693752, "upper": 0.9273646409135352, "order": 41}, {"M": "2012", "seg1": "Ni\u00f1a", "seg2": "Grupo I y II", "cat": "S\u00ed", "prop": 0.07172762016871388, "lower": 0.0, "upper": 0.22434956337376338, "order": 42}, {"M": "2012", "seg1": "Ni\u00f1a", "seg2": "Grupo I y II", "cat": "No", "prop": 0.9282723798312861, "lower": 0.775650436626237, "upper": 1.0, "order": 43}, {"M": "2012", "seg1": "Ni\u00f1a", "seg2": "Grupo III", "cat": "S\u00ed", "prop": 0.28818364780543626, "lower": 0.16110826005056333, "upper": 0.46056149270855645, "order": 44}, {"M": "2012", "seg1": "Ni\u00f1a", "seg2": "Grupo III", "cat": "No", "prop": 0.7118163521945637, "lower": 0.5394385072914436, "upper": 0.8388917399494367, "order": 45}, {"M": "2012", "seg1": "Ni\u00f1a", "seg2": "Grupo IV y V", "cat": "S\u00ed", "prop": 0.24754019591370785, "lower": 0.0793437742530122, "upper": 0.5245155339520584, "order": 46}, {"M": "2012", "seg1": "Ni\u00f1a", "seg2": "Grupo IV y V", "cat": "No", "prop": 0.7524598040862921, "lower": 0.4754844660479417, "upper": 0.9206562257469878, "order": 47}, {"M": "2012", "seg1": "Ni\u00f1a", "seg2": "Grupo VI", "cat": "S\u00ed", "prop": 0.19856907495551834, "lower": 0.1192665585858885, "upper": 0.3062718383621172, "order": 48}, {"M": "2012", "seg1": "Ni\u00f1a", "seg2": "Grupo VI", "cat": "No", "prop": 0.8014309250444817, "lower": 0.6937281616378829, "upper": 0.8807334414141115, "order": 49}, {"M": "2012", "seg1": "Ni\u00f1a", "seg2": "Grupo VII", "cat": "S\u00ed", "prop": 0.12898283786584666, "lower": 0.049315441695792626, "upper": 0.25984627072240096, "order": 50}, {"M": "2012", "seg1": "Ni\u00f1a", "seg2": "Grupo VII", "cat": "No", "prop": 0.8710171621341534, "lower": 0.7401537292775989, "upper": 0.9506845583042074, "order": 51}, {"M": "2012", "seg1": "Ni\u00f1a", "seg2": "No ha trabajado", "cat": "S\u00ed", "prop": 0.10894785940549323, "lower": 0.0, "upper": 0.5248121635923196, "order": 52}, {"M": "2012", "seg1": "Ni\u00f1a", "seg2": "No ha trabajado", "cat": "No", "prop": 0.8910521405945068, "lower": 0.4751878364076804, "upper": 1.0, "order": 53}, {"M": "2012", "seg1": "Ni\u00f1a", "seg2": "Total", "cat": "S\u00ed", "prop": 0.17948371607750996, "lower": 0.12816280681473632, "upper": 0.237152144738857, "order": 54}, {"M": "2012", "seg1": "Ni\u00f1a", "seg2": "Total", "cat": "No", "prop": 0.82051628392249, "lower": 0.7628478552611432, "upper": 0.8718371931852639, "order": 55}, {"M": "2012", "seg1": "Ni\u00f1o", "seg2": "Grupo I y II", "cat": "S\u00ed", "prop": 0.17445821718795174, "lower": 0.0647538058415888, "upper": 0.3410667707522891, "order": 56}, {"M": "2012", "seg1": "Ni\u00f1o", "seg2": "Grupo I y II", "cat": "No", "prop": 0.8255417828120483, "lower": 0.6589332292477114, "upper": 0.9352461941584113, "order": 57}, {"M": "2012", "seg1": "Ni\u00f1o", "seg2": "Grupo III", "cat": "S\u00ed", "prop": 0.06942937038285321, "lower": 0.0, "upper": 0.32267978061238956, "order": 58}, {"M": "2012", "seg1": "Ni\u00f1o", "seg2": "Grupo III", "cat": "No", "prop": 0.9305706296171468, "lower": 0.6773202193876104, "upper": 1.0, "order": 59}, {"M": "2012", "seg1": "Ni\u00f1o", "seg2": "Grupo IV y V", "cat": "S\u00ed", "prop": 0.17085483742239294, "lower": 0.05627623329528588, "upper": 0.40519094410713874, "order": 60}, {"M": "2012", "seg1": "Ni\u00f1o", "seg2": "Grupo IV y V", "cat": "No", "prop": 0.8291451625776071, "lower": 0.5948090558928613, "upper": 0.9437237667047141, "order": 61}, {"M": "2012", "seg1": "Ni\u00f1o", "seg2": "Grupo VI", "cat": "S\u00ed", "prop": 0.12795174012416277, "lower": 0.0667374199865914, "upper": 0.22086068070260514, "order": 62}, {"M": "2012", "seg1": "Ni\u00f1o", "seg2": "Grupo VI", "cat": "No", "prop": 0.8720482598758372, "lower": 0.7791393192973948, "upper": 0.9332625800134084, "order": 63}, {"M": "2012", "seg1": "Ni\u00f1o", "seg2": "Grupo VII", "cat": "S\u00ed", "prop": 0.1323529105149737, "lower": 0.05353169856255583, "upper": 0.2802042495524605, "order": 64}, {"M": "2012", "seg1": "Ni\u00f1o", "seg2": "Grupo VII", "cat": "No", "prop": 0.8676470894850263, "lower": 0.7197957504475394, "upper": 0.9464683014374441, "order": 65}, {"M": "2012", "seg1": "Ni\u00f1o", "seg2": "No ha trabajado", "cat": "S\u00ed", "prop": 0.0971069574328097, "lower": 0.0, "upper": 0.33889028540529675, "order": 66}, {"M": "2012", "seg1": "Ni\u00f1o", "seg2": "No ha trabajado", "cat": "No", "prop": 0.9028930425671903, "lower": 0.6611097145947031, "upper": 1.0, "order": 67}, {"M": "2012", "seg1": "Ni\u00f1o", "seg2": "Total", "cat": "S\u00ed", "prop": 0.13166894026368164, "lower": 0.08739374664200933, "upper": 0.18281116686424342, "order": 68}, {"M": "2012", "seg1": "Ni\u00f1o", "seg2": "Total", "cat": "No", "prop": 0.8683310597363184, "lower": 0.8171888331357557, "upper": 0.9126062533579906, "order": 69}, {"M": "2012", "seg1": "Total", "seg2": "Grupo I y II", "cat": "S\u00ed", "prop": 0.12435874264186031, "lower": 0.05354983702804495, "upper": 0.24063349146976468, "order": 70}, {"M": "2012", "seg1": "Total", "seg2": "Grupo I y II", "cat": "No", "prop": 0.8756412573581397, "lower": 0.7593665085302352, "upper": 0.9464501629719551, "order": 71}, {"M": "2012", "seg1": "Total", "seg2": "Grupo III", "cat": "S\u00ed", "prop": 0.21261220787569335, "lower": 0.12017478041631427, "upper": 0.36021010202728276, "order": 72}, {"M": "2012", "seg1": "Total", "seg2": "Grupo III", "cat": "No", "prop": 0.7873877921243067, "lower": 0.6397898979727172, "upper": 0.8798252195836858, "order": 73}, {"M": "2012", "seg1": "Total", "seg2": "Grupo IV y V", "cat": "S\u00ed", "prop": 0.20758431914534858, "lower": 0.09162234685403044, "upper": 0.37272412138110156, "order": 74}, {"M": "2012", "seg1": "Total", "seg2": "Grupo IV y V", "cat": "No", "prop": 0.7924156808546514, "lower": 0.6272758786188986, "upper": 0.9083776531459695, "order": 75}, {"M": "2012", "seg1": "Total", "seg2": "Grupo VI", "cat": "S\u00ed", "prop": 0.15988976587166479, "lower": 0.10531385037305431, "upper": 0.22183406065649183, "order": 76}, {"M": "2012", "seg1": "Total", "seg2": "Grupo VI", "cat": "No", "prop": 0.8401102341283352, "lower": 0.7781659393435081, "upper": 0.8946861496269454, "order": 77}, {"M": "2012", "seg1": "Total", "seg2": "Grupo VII", "cat": "S\u00ed", "prop": 0.1306313533746864, "lower": 0.06472139014618596, "upper": 0.22356021623076994, "order": 78}, {"M": "2012", "seg1": "Total", "seg2": "Grupo VII", "cat": "No", "prop": 0.8693686466253137, "lower": 0.7764397837692301, "upper": 0.9352786098538141, "order": 79}, {"M": "2012", "seg1": "Total", "seg2": "No ha trabajado", "cat": "S\u00ed", "prop": 0.10111391566441413, "lower": 0.030111694882672776, "upper": 0.27499539980607435, "order": 80}, {"M": "2012", "seg1": "Total", "seg2": "No ha trabajado", "cat": "No", "prop": 0.8988860843355859, "lower": 0.7250046001939257, "upper": 0.9698883051173273, "order": 81}, {"M": "2012", "seg1": "Total", "seg2": "Total", "cat": "S\u00ed", "prop": 0.15498842374651772, "lower": 0.12261513458978186, "upper": 0.19360242692374335, "order": 82}, {"M": "2012", "seg1": "Total", "seg2": "Total", "cat": "No", "prop": 0.8450115762534822, "lower": 0.8063975730762568, "upper": 0.8773848654102181, "order": 83}, {"M": "2016", "seg1": "Ni\u00f1a", "seg2": "Grupo I y II", "cat": "S\u00ed", "prop": 0.17734248486017967, "lower": 0.047424616998104664, "upper": 0.3906115675934784, "order": 84}, {"M": "2016", "seg1": "Ni\u00f1a", "seg2": "Grupo I y II", "cat": "No", "prop": 0.8226575151398203, "lower": 0.6093884324065219, "upper": 0.9525753830018954, "order": 85}, {"M": "2016", "seg1": "Ni\u00f1a", "seg2": "Grupo III", "cat": "S\u00ed", "prop": 0.0, "lower": 0.0, "upper": 0.09494446892524806, "order": 86}, {"M": "2016", "seg1": "Ni\u00f1a", "seg2": "Grupo III", "cat": "No", "prop": 1.0, "lower": 0.9050555310747519, "upper": 1.0, "order": 87}, {"M": "2016", "seg1": "Ni\u00f1a", "seg2": "Grupo IV y V", "cat": "S\u00ed", "prop": 0.28066045728221717, "lower": 0.07296598441334867, "upper": 0.5710719897970961, "order": 88}, {"M": "2016", "seg1": "Ni\u00f1a", "seg2": "Grupo IV y V", "cat": "No", "prop": 0.7193395427177828, "lower": 0.4289280102029043, "upper": 0.9270340155866515, "order": 89}, {"M": "2016", "seg1": "Ni\u00f1a", "seg2": "Grupo VI", "cat": "S\u00ed", "prop": 0.11468954247763198, "lower": 0.05997523536559659, "upper": 0.20045903411070623, "order": 90}, {"M": "2016", "seg1": "Ni\u00f1a", "seg2": "Grupo VI", "cat": "No", "prop": 0.885310457522368, "lower": 0.7995409658892938, "upper": 0.9400247646344034, "order": 91}, {"M": "2016", "seg1": "Ni\u00f1a", "seg2": "Grupo VII", "cat": "S\u00ed", "prop": 0.09663586265480008, "lower": 0.03163577648730035, "upper": 0.2352669543111499, "order": 92}, {"M": "2016", "seg1": "Ni\u00f1a", "seg2": "Grupo VII", "cat": "No", "prop": 0.9033641373451999, "lower": 0.7647330456888499, "upper": 0.9683642235126996, "order": 93}, {"M": "2016", "seg1": "Ni\u00f1a", "seg2": "No ha trabajado", "cat": "S\u00ed", "prop": 0.04331191983996378, "lower": 0.0, "upper": 0.24315165568305488, "order": 94}, {"M": "2016", "seg1": "Ni\u00f1a", "seg2": "No ha trabajado", "cat": "No", "prop": 0.9566880801600363, "lower": 0.7568483443169461, "upper": 1.0, "order": 95}, {"M": "2016", "seg1": "Ni\u00f1a", "seg2": "Total", "cat": "S\u00ed", "prop": 0.11204102553570297, "lower": 0.06885332188252788, "upper": 0.16111941069346378, "order": 96}, {"M": "2016", "seg1": "Ni\u00f1a", "seg2": "Total", "cat": "No", "prop": 0.8879589744642971, "lower": 0.8388805893065362, "upper": 0.9311466781174721, "order": 97}, {"M": "2016", "seg1": "Ni\u00f1o", "seg2": "Grupo I y II", "cat": "S\u00ed", "prop": 0.09119370711528317, "lower": 0.0, "upper": 0.26640852036292195, "order": 98}, {"M": "2016", "seg1": "Ni\u00f1o", "seg2": "Grupo I y II", "cat": "No", "prop": 0.9088062928847168, "lower": 0.733591479637078, "upper": 1.0, "order": 99}, {"M": "2016", "seg1": "Ni\u00f1o", "seg2": "Grupo III", "cat": "S\u00ed", "prop": 0.14782209694710927, "lower": 0.03711182979602207, "upper": 0.3275344444632518, "order": 100}, {"M": "2016", "seg1": "Ni\u00f1o", "seg2": "Grupo III", "cat": "No", "prop": 0.8521779030528908, "lower": 0.6724655555367482, "upper": 0.962888170203978, "order": 101}, {"M": "2016", "seg1": "Ni\u00f1o", "seg2": "Grupo IV y V", "cat": "S\u00ed", "prop": 0.0, "lower": 0.0, "upper": 0.1114522295797616, "order": 102}, {"M": "2016", "seg1": "Ni\u00f1o", "seg2": "Grupo IV y V", "cat": "No", "prop": 1.0, "lower": 0.8885477704202384, "upper": 1.0, "order": 103}, {"M": "2016", "seg1": "Ni\u00f1o", "seg2": "Grupo VI", "cat": "S\u00ed", "prop": 0.09229247019271503, "lower": 0.035544172829213745, "upper": 0.2021086523555511, "order": 104}, {"M": "2016", "seg1": "Ni\u00f1o", "seg2": "Grupo VI", "cat": "No", "prop": 0.907707529807285, "lower": 0.7978913476444489, "upper": 0.9644558271707863, "order": 105}, {"M": "2016", "seg1": "Ni\u00f1o", "seg2": "Grupo VII", "cat": "S\u00ed", "prop": 0.23083930962650545, "lower": 0.11521719279762492, "upper": 0.37878114534920737, "order": 106}, {"M": "2016", "seg1": "Ni\u00f1o", "seg2": "Grupo VII", "cat": "No", "prop": 0.7691606903734945, "lower": 0.6212188546507933, "upper": 0.8847828072023751, "order": 107}, {"M": "2016", "seg1": "Ni\u00f1o", "seg2": "No ha trabajado", "cat": "S\u00ed", "prop": 0.12365089140080579, "lower": 0.0, "upper": 0.44765751839839807, "order": 108}, {"M": "2016", "seg1": "Ni\u00f1o", "seg2": "No ha trabajado", "cat": "No", "prop": 0.8763491085991942, "lower": 0.5523424816016013, "upper": 1.0, "order": 109}, {"M": "2016", "seg1": "Ni\u00f1o", "seg2": "Total", "cat": "S\u00ed", "prop": 0.12607207762970338, "lower": 0.0807809883279691, "upper": 0.18757361745499662, "order": 110}, {"M": "2016", "seg1": "Ni\u00f1o", "seg2": "Total", "cat": "No", "prop": 0.8739279223702966, "lower": 0.8124263825450035, "upper": 0.919219011672031, "order": 111}, {"M": "2016", "seg1": "Total", "seg2": "Grupo I y II", "cat": "S\u00ed", "prop": 0.131830200133474, "lower": 0.05435380547009018, "upper": 0.2434419385262317, "order": 112}, {"M": "2016", "seg1": "Total", "seg2": "Grupo I y II", "cat": "No", "prop": 0.868169799866526, "lower": 0.7565580614737681, "upper": 0.9456461945299098, "order": 113}, {"M": "2016", "seg1": "Total", "seg2": "Grupo III", "cat": "S\u00ed", "prop": 0.09072630377711847, "lower": 0.02310451036151848, "upper": 0.20917966099113874, "order": 114}, {"M": "2016", "seg1": "Total", "seg2": "Grupo III", "cat": "No", "prop": 0.9092736962228816, "lower": 0.7908203390088613, "upper": 0.9768954896384815, "order": 115}, {"M": "2016", "seg1": "Total", "seg2": "Grupo IV y V", "cat": "S\u00ed", "prop": 0.12990095968456786, "lower": 0.03532924190217493, "upper": 0.28964534340215553, "order": 116}, {"M": "2016", "seg1": "Total", "seg2": "Grupo IV y V", "cat": "No", "prop": 0.8700990403154322, "lower": 0.7103546565978445, "upper": 0.9646707580978251, "order": 117}, {"M": "2016", "seg1": "Total", "seg2": "Grupo VI", "cat": "S\u00ed", "prop": 0.10514496937632874, "lower": 0.05882561154856446, "upper": 0.16789274382415123, "order": 118}, {"M": "2016", "seg1": "Total", "seg2": "Grupo VI", "cat": "No", "prop": 0.8948550306236712, "lower": 0.8321072561758488, "upper": 0.9411743884514356, "order": 119}, {"M": "2016", "seg1": "Total", "seg2": "Grupo VII", "cat": "S\u00ed", "prop": 0.1625068056205932, "lower": 0.0938199591431541, "upper": 0.27151389437072143, "order": 120}, {"M": "2016", "seg1": "Total", "seg2": "Grupo VII", "cat": "No", "prop": 0.8374931943794068, "lower": 0.7284861056292786, "upper": 0.9061800408568459, "order": 121}, {"M": "2016", "seg1": "Total", "seg2": "No ha trabajado", "cat": "S\u00ed", "prop": 0.07776107093346432, "lower": 0.024336389221180622, "upper": 0.2190635659252873, "order": 122}, {"M": "2016", "seg1": "Total", "seg2": "No ha trabajado", "cat": "No", "prop": 0.9222389290665357, "lower": 0.7809364340747129, "upper": 0.9756636107788194, "order": 123}, {"M": "2016", "seg1": "Total", "seg2": "Total", "cat": "S\u00ed", "prop": 0.11888736644105719, "lower": 0.08891267300899588, "upper": 0.15532701689216133, "order": 124}, {"M": "2016", "seg1": "Total", "seg2": "Total", "cat": "No", "prop": 0.8811126335589429, "lower": 0.8446729831078386, "upper": 0.911087326991004, "order": 125}, {"M": "2023", "seg1": "Ni\u00f1a", "seg2": "Grupo I y II", "cat": "S\u00ed", "prop": 0.12344920953464095, "lower": 0.04439350904091682, "upper": 0.2528209743945577, "order": 126}, {"M": "2023", "seg1": "Ni\u00f1a", "seg2": "Grupo I y II", "cat": "No", "prop": 0.876550790465359, "lower": 0.7471790256054425, "upper": 0.9556064909590831, "order": 127}, {"M": "2023", "seg1": "Ni\u00f1a", "seg2": "Grupo III", "cat": "S\u00ed", "prop": 0.0409736108223607, "lower": 0.0, "upper": 0.13971657439314908, "order": 128}, {"M": "2023", "seg1": "Ni\u00f1a", "seg2": "Grupo III", "cat": "No", "prop": 0.9590263891776394, "lower": 0.8602834256068522, "upper": 1.0, "order": 129}, {"M": "2023", "seg1": "Ni\u00f1a", "seg2": "Grupo IV y V", "cat": "S\u00ed", "prop": 0.0, "lower": 0.0, "upper": 0.10534757730523049, "order": 130}, {"M": "2023", "seg1": "Ni\u00f1a", "seg2": "Grupo IV y V", "cat": "No", "prop": 1.0, "lower": 0.8946524226947695, "upper": 1.0, "order": 131}, {"M": "2023", "seg1": "Ni\u00f1a", "seg2": "Grupo VI", "cat": "S\u00ed", "prop": 0.1080936385303574, "lower": 0.02601973579079816, "upper": 0.2556056720389557, "order": 132}, {"M": "2023", "seg1": "Ni\u00f1a", "seg2": "Grupo VI", "cat": "No", "prop": 0.8919063614696426, "lower": 0.7443943279610444, "upper": 0.9739802642092018, "order": 133}, {"M": "2023", "seg1": "Ni\u00f1a", "seg2": "Grupo VII", "cat": "S\u00ed", "prop": 0.013528631064992951, "lower": 0.0, "upper": 0.07017063432970594, "order": 134}, {"M": "2023", "seg1": "Ni\u00f1a", "seg2": "Grupo VII", "cat": "No", "prop": 0.986471368935007, "lower": 0.9298293656702941, "upper": 1.0, "order": 135}, {"M": "2023", "seg1": "Ni\u00f1a", "seg2": "No ha trabajado", "cat": "S\u00ed", "prop": 0.19131419916230674, "lower": 0.0461018267971264, "upper": 0.42466609610802064, "order": 136}, {"M": "2023", "seg1": "Ni\u00f1a", "seg2": "No ha trabajado", "cat": "No", "prop": 0.8086858008376934, "lower": 0.5753339038919792, "upper": 0.9538981732028736, "order": 137}, {"M": "2023", "seg1": "Ni\u00f1a", "seg2": "Total", "cat": "S\u00ed", "prop": 0.0856014668568404, "lower": 0.04727747334104575, "upper": 0.1411254655172154, "order": 138}, {"M": "2023", "seg1": "Ni\u00f1a", "seg2": "Total", "cat": "No", "prop": 0.9143985331431596, "lower": 0.8588745344827847, "upper": 0.9527225266589543, "order": 139}, {"M": "2023", "seg1": "Ni\u00f1o", "seg2": "Grupo I y II", "cat": "S\u00ed", "prop": 0.06056156835693918, "lower": 0.0, "upper": 0.19498789026091357, "order": 140}, {"M": "2023", "seg1": "Ni\u00f1o", "seg2": "Grupo I y II", "cat": "No", "prop": 0.939438431643061, "lower": 0.8050121097390863, "upper": 1.0, "order": 141}, {"M": "2023", "seg1": "Ni\u00f1o", "seg2": "Grupo III", "cat": "S\u00ed", "prop": 0.04448043331750197, "lower": 0.0, "upper": 0.1957580138975053, "order": 142}, {"M": "2023", "seg1": "Ni\u00f1o", "seg2": "Grupo III", "cat": "No", "prop": 0.9555195666824983, "lower": 0.8042419861024918, "upper": 1.0, "order": 143}, {"M": "2023", "seg1": "Ni\u00f1o", "seg2": "Grupo IV y V", "cat": "S\u00ed", "prop": 0.06347521142321054, "lower": 0.0, "upper": 0.20669516525119047, "order": 144}, {"M": "2023", "seg1": "Ni\u00f1o", "seg2": "Grupo IV y V", "cat": "No", "prop": 0.9365247885767896, "lower": 0.7933048347488096, "upper": 1.0, "order": 145}, {"M": "2023", "seg1": "Ni\u00f1o", "seg2": "Grupo VI", "cat": "S\u00ed", "prop": 0.06352955644334038, "lower": 0.022580184825878924, "upper": 0.1390346863405132, "order": 146}, {"M": "2023", "seg1": "Ni\u00f1o", "seg2": "Grupo VI", "cat": "No", "prop": 0.9364704435566596, "lower": 0.8609653136594868, "upper": 0.977419815174121, "order": 147}, {"M": "2023", "seg1": "Ni\u00f1o", "seg2": "Grupo VII", "cat": "S\u00ed", "prop": 0.037345302884096654, "lower": 0.0, "upper": 0.1029672462652192, "order": 148}, {"M": "2023", "seg1": "Ni\u00f1o", "seg2": "Grupo VII", "cat": "No", "prop": 0.9626546971159033, "lower": 0.897032753734781, "upper": 1.0, "order": 149}, {"M": "2023", "seg1": "Ni\u00f1o", "seg2": "No ha trabajado", "cat": "S\u00ed", "prop": 0.056383045388269735, "lower": 0.0, "upper": 0.24331204382788318, "order": 150}, {"M": "2023", "seg1": "Ni\u00f1o", "seg2": "No ha trabajado", "cat": "No", "prop": 0.9436169546117303, "lower": 0.7566879561721166, "upper": 1.0, "order": 151}, {"M": "2023", "seg1": "Ni\u00f1o", "seg2": "Total", "cat": "S\u00ed", "prop": 0.05464546861115529, "lower": 0.028452703256607627, "upper": 0.09297734119337417, "order": 152}, {"M": "2023", "seg1": "Ni\u00f1o", "seg2": "Total", "cat": "No", "prop": 0.9453545313888446, "lower": 0.9070226588066264, "upper": 0.9715472967433925, "order": 153}, {"M": "2023", "seg1": "Total", "seg2": "Grupo I y II", "cat": "S\u00ed", "prop": 0.08834443727210184, "lower": 0.04048287684005036, "upper": 0.17324048722306284, "order": 154}, {"M": "2023", "seg1": "Total", "seg2": "Grupo I y II", "cat": "No", "prop": 0.9116555627278982, "lower": 0.8267595127769372, "upper": 0.9595171231599496, "order": 155}, {"M": "2023", "seg1": "Total", "seg2": "Grupo III", "cat": "S\u00ed", "prop": 0.042729267705823186, "lower": 0.008259347718307906, "upper": 0.12954288962530175, "order": 156}, {"M": "2023", "seg1": "Total", "seg2": "Grupo III", "cat": "No", "prop": 0.9572707322941768, "lower": 0.8704571103746984, "upper": 0.9917406522816921, "order": 157}, {"M": "2023", "seg1": "Total", "seg2": "Grupo IV y V", "cat": "S\u00ed", "prop": 0.04082579751380385, "lower": 0.0, "upper": 0.1457671440703211, "order": 158}, {"M": "2023", "seg1": "Total", "seg2": "Grupo IV y V", "cat": "No", "prop": 0.9591742024861963, "lower": 0.8542328559296789, "upper": 1.0, "order": 159}, {"M": "2023", "seg1": "Total", "seg2": "Grupo VI", "cat": "S\u00ed", "prop": 0.08927236648587071, "lower": 0.038430177313452954, "upper": 0.1665685686464988, "order": 160}, {"M": "2023", "seg1": "Total", "seg2": "Grupo VI", "cat": "No", "prop": 0.9107276335141293, "lower": 0.8334314313535012, "upper": 0.961569822686547, "order": 161}, {"M": "2023", "seg1": "Total", "seg2": "Grupo VII", "cat": "S\u00ed", "prop": 0.02673466544787273, "lower": 0.005969297493648549, "upper": 0.07436044217094757, "order": 162}, {"M": "2023", "seg1": "Total", "seg2": "Grupo VII", "cat": "No", "prop": 0.9732653345521273, "lower": 0.925639557829052, "upper": 0.9940307025063514, "order": 163}, {"M": "2023", "seg1": "Total", "seg2": "No ha trabajado", "cat": "S\u00ed", "prop": 0.11630347804569942, "lower": 0.04410271713139335, "upper": 0.26494816434427815, "order": 164}, {"M": "2023", "seg1": "Total", "seg2": "No ha trabajado", "cat": "No", "prop": 0.8836965219543005, "lower": 0.7350518356557221, "upper": 0.9558972828686066, "order": 165}, {"M": "2023", "seg1": "Total", "seg2": "Total", "cat": "S\u00ed", "prop": 0.06995233630396154, "lower": 0.048053562169048464, "upper": 0.10634648305424484, "order": 166}, {"M": "2023", "seg1": "Total", "seg2": "Total", "cat": "No", "prop": 0.9300476636960385, "lower": 0.8936535169457551, "upper": 0.9519464378309516, "order": 167}]}}